{".class": "MypyFile", "_fullname": "baby.training.cnn_trainer", "is_partial_stub_package": false, "is_stub": false, "names": {".class": "SymbolTable", "Augmenter": {".class": "SymbolTableNode", "cross_ref": "baby.augmentation.Augmenter", "kind": "Gdef"}, "BadProcess": {".class": "SymbolTableNode", "cross_ref": "baby.errors.BadProcess", "kind": "Gdef"}, "BadType": {".class": "SymbolTableNode", "cross_ref": "baby.errors.BadType", "kind": "Gdef"}, "CNNTrainer": {".class": "SymbolTableNode", "kind": "Gdef", "node": {".class": "TypeInfo", "_promote": null, "abstract_attributes": [], "bases": ["builtins.object"], "declared_metaclass": null, "defn": {".class": "ClassDef", "fullname": "baby.training.cnn_trainer.CNNTrainer", "name": "CNNTrainer", "type_vars": []}, "flags": [], "fullname": "baby.training.cnn_trainer.CNNTrainer", "metaclass_type": null, "metadata": {}, "module_name": "baby.training.cnn_trainer", "mro": ["baby.training.cnn_trainer.CNNTrainer", "builtins.object"], "names": {".class": "SymbolTable", "__init__": {".class": "SymbolTableNode", "kind": "Mdef", "node": {".class": "FuncDef", "arg_kinds": [0, 0, 0, 0, 0, 0, 1, 1], "arg_names": ["self", "save_dir", "cnn_set", "gen", "aug", "flattener", "max_cnns", "cnn_fn"], "flags": [], "fullname": "baby.training.cnn_trainer.CNNTrainer.__init__", "name": "__init__", "type": {".class": "CallableType", "arg_kinds": [0, 0, 0, 0, 0, 0, 1, 1], "arg_names": ["self", "save_dir", "cnn_set", "gen", "aug", "flattener", "max_cnns", "cnn_fn"], "arg_types": ["baby.training.cnn_trainer.CNNTrainer", "pathlib.Path", {".class": "Instance", "args": [{".class": "AnyType", "missing_import_name": null, "source_any": null, "type_of_any": 4}], "type_ref": "builtins.tuple"}, "baby.generator.ImageLabel", "baby.augmentation.Augmenter", "baby.preprocessing.SegmentationFlattening", "builtins.int", {".class": "UnionType", "items": ["builtins.str", {".class": "NoneType"}]}], "bound_args": [], "def_extras": {"first_arg": "self"}, "fallback": "builtins.function", "implicit": false, "is_ellipsis_args": false, "name": "__init__ of CNNTrainer", "ret_type": {".class": "NoneType"}, "type_guard": null, "variables": []}}}, "_cnn_fn": {".class": "SymbolTableNode", "implicit": true, "kind": "Mdef", "node": {".class": "Var", "flags": [], "fullname": "baby.training.cnn_trainer.CNNTrainer._cnn_fn", "name": "_cnn_fn", "type": {".class": "UnionType", "items": ["builtins.str", {".class": "NoneType"}]}}}, "_cnns": {".class": "SymbolTableNode", "implicit": true, "kind": "Mdef", "node": {".class": "Var", "flags": [], "fullname": "baby.training.cnn_trainer.CNNTrainer._cnns", "name": "_cnns", "type": {".class": "Instance", "args": [{".class": "AnyType", "missing_import_name": null, "source_any": null, "type_of_any": 1}, {".class": "AnyType", "missing_import_name": null, "source_any": null, "type_of_any": 1}], "type_ref": "builtins.dict"}}}, "_max_cnns": {".class": "SymbolTableNode", "implicit": true, "kind": "Mdef", "node": {".class": "Var", "flags": [], "fullname": "baby.training.cnn_trainer.CNNTrainer._max_cnns", "name": "_max_cnns", "type": "builtins.int"}}, "_opt_cnn": {".class": "SymbolTableNode", "implicit": true, "kind": "Mdef", "node": {".class": "Var", "flags": [], "fullname": "baby.training.cnn_trainer.CNNTrainer._opt_cnn", "name": "_opt_cnn", "type": {".class": "NoneType"}}}, "aug": {".class": "SymbolTableNode", "implicit": true, "kind": "Mdef", "node": {".class": "Var", "flags": [], "fullname": "baby.training.cnn_trainer.CNNTrainer.aug", "name": "aug", "type": "baby.augmentation.Augmenter"}}, "cnn": {".class": "SymbolTableNode", "kind": "Mdef", "node": {".class": "Decorator", "func": {".class": "FuncDef", "arg_kinds": [0], "arg_names": ["self"], "flags": ["is_property", "is_decorated"], "fullname": "baby.training.cnn_trainer.CNNTrainer.cnn", "name": "cnn", "type": null}, "is_overload": false, "var": {".class": "Var", "flags": ["is_initialized_in_class", "is_property", "is_ready"], "fullname": null, "name": "cnn", "type": {".class": "CallableType", "arg_kinds": [0], "arg_names": ["self"], "arg_types": ["baby.training.cnn_trainer.CNNTrainer"], "bound_args": [], "def_extras": {"first_arg": "self"}, "fallback": "builtins.function", "implicit": true, "is_ellipsis_args": false, "name": "cnn of CNNTrainer", "ret_type": {".class": "AnyType", "missing_import_name": null, "source_any": null, "type_of_any": 1}, "type_guard": null, "variables": []}}}}, "cnn_dir": {".class": "SymbolTableNode", "kind": "Mdef", "node": {".class": "Decorator", "func": {".class": "FuncDef", "arg_kinds": [0], "arg_names": ["self"], "flags": ["is_property", "is_decorated"], "fullname": "baby.training.cnn_trainer.CNNTrainer.cnn_dir", "name": "cnn_dir", "type": null}, "is_overload": false, "var": {".class": "Var", "flags": ["is_initialized_in_class", "is_property", "is_ready"], "fullname": null, "name": "cnn_dir", "type": {".class": "CallableType", "arg_kinds": [0], "arg_names": ["self"], "arg_types": ["baby.training.cnn_trainer.CNNTrainer"], "bound_args": [], "def_extras": {"first_arg": "self"}, "fallback": "builtins.function", "implicit": true, "is_ellipsis_args": false, "name": "cnn_dir of CNNTrainer", "ret_type": {".class": "AnyType", "missing_import_name": null, "source_any": null, "type_of_any": 1}, "type_guard": null, "variables": []}}}}, "cnn_fn": {".class": "SymbolTableNode", "kind": "Mdef", "node": {".class": "OverloadedFuncDef", "flags": ["is_property"], "fullname": "baby.training.cnn_trainer.CNNTrainer.cnn_fn", "impl": null, "items": [{".class": "Decorator", "func": {".class": "FuncDef", "arg_kinds": [0], "arg_names": ["self"], "flags": ["is_property", "is_overload", "is_decorated"], "fullname": "baby.training.cnn_trainer.CNNTrainer.cnn_fn", "name": "cnn_fn", "type": null}, "is_overload": true, "var": {".class": "Var", "flags": ["is_initialized_in_class", "is_property", "is_settable_property", "is_ready"], "fullname": null, "name": "cnn_fn", "type": {".class": "CallableType", "arg_kinds": [0], "arg_names": ["self"], "arg_types": ["baby.training.cnn_trainer.CNNTrainer"], "bound_args": [], "def_extras": {"first_arg": "self"}, "fallback": "builtins.function", "implicit": true, "is_ellipsis_args": false, "name": "cnn_fn of CNNTrainer", "ret_type": {".class": "AnyType", "missing_import_name": null, "source_any": null, "type_of_any": 1}, "type_guard": null, "variables": []}}}, {".class": "Decorator", "func": {".class": "FuncDef", "arg_kinds": [0, 0], "arg_names": ["self", "fn"], "flags": ["is_decorated"], "fullname": "baby.training.cnn_trainer.CNNTrainer.cnn_fn", "name": "cnn_fn", "type": null}, "is_overload": false, "var": {".class": "Var", "flags": [], "fullname": null, "name": "cnn_fn", "type": null}}], "type": {".class": "Overloaded", "items": [{".class": "CallableType", "arg_kinds": [0], "arg_names": ["self"], "arg_types": ["baby.training.cnn_trainer.CNNTrainer"], "bound_args": [], "def_extras": {"first_arg": "self"}, "fallback": "builtins.function", "implicit": true, "is_ellipsis_args": false, "name": "cnn_fn", "ret_type": {".class": "AnyType", "missing_import_name": null, "source_any": null, "type_of_any": 1}, "type_guard": null, "variables": []}]}}}, "cnn_name": {".class": "SymbolTableNode", "kind": "Mdef", "node": {".class": "Decorator", "func": {".class": "FuncDef", "arg_kinds": [0], "arg_names": ["self"], "flags": ["is_property", "is_decorated"], "fullname": "baby.training.cnn_trainer.CNNTrainer.cnn_name", "name": "cnn_name", "type": null}, "is_overload": false, "var": {".class": "Var", "flags": ["is_initialized_in_class", "is_property", "is_ready"], "fullname": null, "name": "cnn_name", "type": {".class": "CallableType", "arg_kinds": [0], "arg_names": ["self"], "arg_types": ["baby.training.cnn_trainer.CNNTrainer"], "bound_args": [], "def_extras": {"first_arg": "self"}, "fallback": "builtins.function", "implicit": true, "is_ellipsis_args": false, "name": "cnn_name of CNNTrainer", "ret_type": {".class": "AnyType", "missing_import_name": null, "source_any": null, "type_of_any": 1}, "type_guard": null, "variables": []}}}}, "cnn_set": {".class": "SymbolTableNode", "implicit": true, "kind": "Mdef", "node": {".class": "Var", "flags": [], "fullname": "baby.training.cnn_trainer.CNNTrainer.cnn_set", "name": "cnn_set", "type": {".class": "Instance", "args": [{".class": "AnyType", "missing_import_name": null, "source_any": null, "type_of_any": 4}], "type_ref": "builtins.tuple"}}}, "fit": {".class": "SymbolTableNode", "kind": "Mdef", "node": {".class": "FuncDef", "arg_kinds": [0, 1, 1, 1, 1], "arg_names": ["self", "epochs", "schedule", "replace", "extend"], "flags": [], "fullname": "baby.training.cnn_trainer.CNNTrainer.fit", "name": "fit", "type": {".class": "CallableType", "arg_kinds": [0, 1, 1, 1, 1], "arg_names": ["self", "epochs", "schedule", "replace", "extend"], "arg_types": ["baby.training.cnn_trainer.CNNTrainer", "builtins.int", {".class": "UnionType", "items": [{".class": "Instance", "args": [{".class": "TupleType", "implicit": false, "items": ["builtins.int", "builtins.float"], "partial_fallback": {".class": "Instance", "args": [{".class": "AnyType", "missing_import_name": null, "source_any": null, "type_of_any": 6}], "type_ref": "builtins.tuple"}}], "type_ref": "builtins.list"}, {".class": "NoneType"}]}, "builtins.bool", "builtins.bool"], "bound_args": [], "def_extras": {"first_arg": "self"}, "fallback": "builtins.function", "implicit": false, "is_ellipsis_args": false, "name": "fit of CNNTrainer", "ret_type": {".class": "AnyType", "missing_import_name": null, "source_any": null, "type_of_any": 1}, "type_guard": null, "variables": []}}}, "flattener": {".class": "SymbolTableNode", "implicit": true, "kind": "Mdef", "node": {".class": "Var", "flags": [], "fullname": "baby.training.cnn_trainer.CNNTrainer.flattener", "name": "flattener", "type": "baby.preprocessing.SegmentationFlattening"}}, "gen": {".class": "SymbolTableNode", "implicit": true, "kind": "Mdef", "node": {".class": "Var", "flags": [], "fullname": "baby.training.cnn_trainer.CNNTrainer.gen", "name": "gen", "type": "baby.generator.ImageLabel"}}, "histories": {".class": "SymbolTableNode", "kind": "Mdef", "node": {".class": "Decorator", "func": {".class": "FuncDef", "arg_kinds": [0], "arg_names": ["self"], "flags": ["is_property", "is_decorated"], "fullname": "baby.training.cnn_trainer.CNNTrainer.histories", "name": "histories", "type": null}, "is_overload": false, "var": {".class": "Var", "flags": ["is_initialized_in_class", "is_property", "is_ready"], "fullname": null, "name": "histories", "type": {".class": "CallableType", "arg_kinds": [0], "arg_names": ["self"], "arg_types": ["baby.training.cnn_trainer.CNNTrainer"], "bound_args": [], "def_extras": {"first_arg": "self"}, "fallback": "builtins.function", "implicit": true, "is_ellipsis_args": false, "name": "histories of CNNTrainer", "ret_type": {".class": "AnyType", "missing_import_name": null, "source_any": null, "type_of_any": 1}, "type_guard": null, "variables": []}}}}, "opt_cnn": {".class": "SymbolTableNode", "kind": "Mdef", "node": {".class": "Decorator", "func": {".class": "FuncDef", "arg_kinds": [0], "arg_names": ["self"], "flags": ["is_property", "is_decorated"], "fullname": "baby.training.cnn_trainer.CNNTrainer.opt_cnn", "name": "opt_cnn", "type": null}, "is_overload": false, "var": {".class": "Var", "flags": ["is_initialized_in_class", "is_property", "is_ready"], "fullname": null, "name": "opt_cnn", "type": {".class": "CallableType", "arg_kinds": [0], "arg_names": ["self"], "arg_types": ["baby.training.cnn_trainer.CNNTrainer"], "bound_args": [], "def_extras": {"first_arg": "self"}, "fallback": "builtins.function", "implicit": true, "is_ellipsis_args": false, "name": "opt_cnn of CNNTrainer", "ret_type": {".class": "AnyType", "missing_import_name": null, "source_any": null, "type_of_any": 1}, "type_guard": null, "variables": []}}}}, "opt_dir": {".class": "SymbolTableNode", "kind": "Mdef", "node": {".class": "Decorator", "func": {".class": "FuncDef", "arg_kinds": [0], "arg_names": ["self"], "flags": ["is_property", "is_decorated"], "fullname": "baby.training.cnn_trainer.CNNTrainer.opt_dir", "name": "opt_dir", "type": null}, "is_overload": false, "var": {".class": "Var", "flags": ["is_initialized_in_class", "is_property", "is_ready"], "fullname": null, "name": "opt_dir", "type": {".class": "CallableType", "arg_kinds": [0], "arg_names": ["self"], "arg_types": ["baby.training.cnn_trainer.CNNTrainer"], "bound_args": [], "def_extras": {"first_arg": "self"}, "fallback": "builtins.function", "implicit": true, "is_ellipsis_args": false, "name": "opt_dir of CNNTrainer", "ret_type": {".class": "AnyType", "missing_import_name": null, "source_any": null, "type_of_any": 1}, "type_guard": null, "variables": []}}}}, "plot_histories": {".class": "SymbolTableNode", "kind": "Mdef", "node": {".class": "FuncDef", "arg_kinds": [0, 1, 1, 1, 1, 1, 1], "arg_names": ["self", "key", "log", "window", "ax", "save", "legend"], "flags": [], "fullname": "baby.training.cnn_trainer.CNNTrainer.plot_histories", "name": "plot_histories", "type": {".class": "CallableType", "arg_kinds": [0, 1, 1, 1, 1, 1, 1], "arg_names": ["self", "key", "log", "window", "ax", "save", "legend"], "arg_types": ["baby.training.cnn_trainer.CNNTrainer", "builtins.str", "builtins.bool", "builtins.int", {".class": "UnionType", "items": [{".class": "AnyType", "missing_import_name": null, "source_any": null, "type_of_any": 6}, {".class": "NoneType"}]}, "builtins.bool", "builtins.bool"], "bound_args": [], "def_extras": {"first_arg": "self"}, "fallback": "builtins.function", "implicit": false, "is_ellipsis_args": false, "name": "plot_histories of CNNTrainer", "ret_type": {".class": "AnyType", "missing_import_name": null, "source_any": null, "type_of_any": 1}, "type_guard": null, "variables": []}}}, "save_dir": {".class": "SymbolTableNode", "implicit": true, "kind": "Mdef", "node": {".class": "Var", "flags": [], "fullname": "baby.training.cnn_trainer.CNNTrainer.save_dir", "name": "save_dir", "type": "pathlib.Path"}}}, "tuple_type": null, "type_vars": [], "typeddict_type": null}}, "FINAL_WEIGHTS_FILE": {".class": "SymbolTableNode", "kind": "Gdef", "node": {".class": "Var", "flags": ["is_ready", "has_explicit_value"], "fullname": "baby.training.cnn_trainer.FINAL_WEIGHTS_FILE", "name": "FINAL_WEIGHTS_FILE", "type": "builtins.str"}}, "HISTORY_FILE": {".class": "SymbolTableNode", "kind": "Gdef", "node": {".class": "Var", "flags": ["is_ready", "has_explicit_value"], "fullname": "baby.training.cnn_trainer.HISTORY_FILE", "name": "HISTORY_FILE", "type": "builtins.str"}}, "INIT_WEIGHTS_FILE": {".class": "SymbolTableNode", "kind": "Gdef", "node": {".class": "Var", "flags": ["is_ready", "has_explicit_value"], "fullname": "baby.training.cnn_trainer.INIT_WEIGHTS_FILE", "name": "INIT_WEIGHTS_FILE", "type": "builtins.str"}}, "ImageLabel": {".class": "SymbolTableNode", "cross_ref": "baby.generator.ImageLabel", "kind": "Gdef"}, "LOG_DIR": {".class": "SymbolTableNode", "kind": "Gdef", "node": {".class": "Var", "flags": ["is_ready", "has_explicit_value"], "fullname": "baby.training.cnn_trainer.LOG_DIR", "name": "LOG_DIR", "type": "builtins.str"}}, "LearningRateScheduler": {".class": "SymbolTableNode", "kind": "Gdef", "node": {".class": "Var", "flags": ["is_suppressed_import", "is_ready"], "fullname": "baby.training.cnn_trainer.LearningRateScheduler", "name": "LearningRateScheduler", "type": {".class": "AnyType", "missing_import_name": "baby.training.cnn_trainer.LearningRateScheduler", "source_any": null, "type_of_any": 3}}}, "List": {".class": "SymbolTableNode", "cross_ref": "typing.List", "kind": "Gdef"}, "ModelCheckpoint": {".class": "SymbolTableNode", "kind": "Gdef", "node": {".class": "Var", "flags": ["is_suppressed_import", "is_ready"], "fullname": "baby.training.cnn_trainer.ModelCheckpoint", "name": "ModelCheckpoint", "type": {".class": "AnyType", "missing_import_name": "baby.training.cnn_trainer.ModelCheckpoint", "source_any": null, "type_of_any": 3}}}, "OPT_WEIGHTS_FILE": {".class": "SymbolTableNode", "kind": "Gdef", "node": {".class": "Var", "flags": ["is_ready", "has_explicit_value"], "fullname": "baby.training.cnn_trainer.OPT_WEIGHTS_FILE", "name": "OPT_WEIGHTS_FILE", "type": "builtins.str"}}, "SegmentationFlattening": {".class": "SymbolTableNode", "cross_ref": "baby.preprocessing.SegmentationFlattening", "kind": "Gdef"}, "TensorBoard": {".class": "SymbolTableNode", "kind": "Gdef", "node": {".class": "Var", "flags": ["is_suppressed_import", "is_ready"], "fullname": "baby.training.cnn_trainer.TensorBoard", "name": "TensorBoard", "type": {".class": "AnyType", "missing_import_name": "baby.training.cnn_trainer.TensorBoard", "source_any": null, "type_of_any": 3}}}, "Tuple": {".class": "SymbolTableNode", "cross_ref": "typing.Tuple", "kind": "Gdef"}, "__doc__": {".class": "SymbolTableNode", "kind": "Gdef", "node": {".class": "Var", "flags": ["is_ready"], "fullname": "baby.training.cnn_trainer.__doc__", "name": "__doc__", "type": "builtins.str"}}, "__file__": {".class": "SymbolTableNode", "kind": "Gdef", "node": {".class": "Var", "flags": ["is_ready"], "fullname": "baby.training.cnn_trainer.__file__", "name": "__file__", "type": "builtins.str"}}, "__name__": {".class": "SymbolTableNode", "kind": "Gdef", "node": {".class": "Var", "flags": ["is_ready"], "fullname": "baby.training.cnn_trainer.__name__", "name": "__name__", "type": "builtins.str"}}, "__package__": {".class": "SymbolTableNode", "kind": "Gdef", "node": {".class": "Var", "flags": ["is_ready"], "fullname": "baby.training.cnn_trainer.__package__", "name": "__package__", "type": "builtins.str"}}, "bce_dice_loss": {".class": "SymbolTableNode", "cross_ref": "baby.losses.bce_dice_loss", "kind": "Gdef"}, "custom_objects": {".class": "SymbolTableNode", "kind": "Gdef", "node": {".class": "Var", "flags": ["has_explicit_value"], "fullname": "baby.training.cnn_trainer.custom_objects", "name": "custom_objects", "type": {".class": "Instance", "args": ["builtins.str", {".class": "CallableType", "arg_kinds": [0, 0], "arg_names": ["y_true", "y_pred"], "arg_types": [{".class": "AnyType", "missing_import_name": null, "source_any": null, "type_of_any": 1}, {".class": "AnyType", "missing_import_name": null, "source_any": null, "type_of_any": 1}], "bound_args": [], "def_extras": {"first_arg": null}, "fallback": "builtins.function", "implicit": true, "is_ellipsis_args": false, "name": null, "ret_type": {".class": "AnyType", "missing_import_name": null, "source_any": null, "type_of_any": 1}, "type_guard": null, "variables": []}], "type_ref": "builtins.dict"}}}, "dice_coeff": {".class": "SymbolTableNode", "cross_ref": "baby.losses.dice_coeff", "kind": "Gdef"}, "get_name": {".class": "SymbolTableNode", "cross_ref": "baby.utils.get_name", "kind": "Gdef"}, "json": {".class": "SymbolTableNode", "cross_ref": "json", "kind": "Gdef"}, "load_model": {".class": "SymbolTableNode", "kind": "Gdef", "node": {".class": "Var", "flags": ["is_suppressed_import", "is_ready"], "fullname": "baby.training.cnn_trainer.load_model", "name": "load_model", "type": {".class": "AnyType", "missing_import_name": "baby.training.cnn_trainer.load_model", "source_any": null, "type_of_any": 3}}}, "models": {".class": "SymbolTableNode", "cross_ref": "baby.models", "kind": "Gdef"}, "pathlib": {".class": "SymbolTableNode", "cross_ref": "pathlib", "kind": "Gdef"}, "pickle": {".class": "SymbolTableNode", "cross_ref": "pickle", "kind": "Gdef"}, "plt": {".class": "SymbolTableNode", "cross_ref": "matplotlib.pyplot", "kind": "Gdef"}, "savgol_filter": {".class": "SymbolTableNode", "kind": "Gdef", "node": {".class": "Var", "flags": ["is_suppressed_import", "is_ready"], "fullname": "baby.training.cnn_trainer.savgol_filter", "name": "savgol_filter", "type": {".class": "AnyType", "missing_import_name": "baby.training.cnn_trainer.savgol_filter", "source_any": null, "type_of_any": 3}}}, "schedule_steps": {".class": "SymbolTableNode", "cross_ref": "baby.utils.schedule_steps", "kind": "Gdef"}, "tf": {".class": "SymbolTableNode", "kind": "Gdef", "node": {".class": "Var", "flags": ["is_suppressed_import", "is_ready"], "fullname": "baby.training.cnn_trainer.tf", "name": "tf", "type": {".class": "AnyType", "missing_import_name": "baby.training.cnn_trainer.tf", "source_any": null, "type_of_any": 3}}}, "to_rgba": {".class": "SymbolTableNode", "kind": "Gdef", "node": {".class": "Var", "flags": ["is_suppressed_import", "is_ready"], "fullname": "baby.training.cnn_trainer.to_rgba", "name": "to_rgba", "type": {".class": "AnyType", "missing_import_name": "baby.training.cnn_trainer.to_rgba", "source_any": null, "type_of_any": 3}}}}, "path": "/home/alan/Documents/dev/libs/baby/baby/training/cnn_trainer.py"}